{
"type": "FeatureCollection",
"name": "a3e989424426_visibility",
"crs": { "type": "name", "properties": { "name": "urn:ogc:def:crs:OGC:1.3:CRS84" } },
"features": [
{ "type": "Feature", "properties": { "visible_points": 7, "total_points": 49, "visibility_pct": 14.285714285714285 }, "geometry": { "type": "Point", "coordinates": [ -2.159468007053477, 54.959213428953717 ] } },
{ "type": "Feature", "properties": { "visible_points": 3, "total_points": 48, "visibility_pct": 6.25 }, "geometry": { "type": "Point", "coordinates": [ -2.159251621920796, 54.959213713696712 ] } },
{ "type": "Feature", "properties": { "visible_points": 6, "total_points": 55, "visibility_pct": 10.909090909090908 }, "geometry": { "type": "Point", "coordinates": [ -2.159576628951118, 54.959321119789905 ] } },
{ "type": "Feature", "properties": { "visible_points": 5, "total_points": 54, "visibility_pct": 9.2592592592592595 }, "geometry": { "type": "Point", "coordinates": [ -2.159360243243961, 54.959321404724648 ] } },
{ "type": "Feature", "properties": { "visible_points": 5, "total_points": 52, "visibility_pct": 9.6153846153846168 }, "geometry": { "type": "Point", "coordinates": [ -2.159143857533032, 54.95932168927429 ] } },
{ "type": "Feature", "properties": { "visible_points": 0, "total_points": 48, "visibility_pct": 0.0 }, "geometry": { "type": "Point", "coordinates": [ -2.158927471818346, 54.95932197343889 ] } },
{ "type": "Feature", "properties": { "visible_points": 6, "total_points": 55, "visibility_pct": 10.909090909090908 }, "geometry": { "type": "Point", "coordinates": [ -2.159685251426994, 54.959428810528685 ] } },
{ "type": "Feature", "properties": { "visible_points": 4, "total_points": 55, "visibility_pct": 7.2727272727272725 }, "geometry": { "type": "Point", "coordinates": [ -2.159468865145354, 54.959429095655175 ] } },
{ "type": "Feature", "properties": { "visible_points": 5, "total_points": 55, "visibility_pct": 9.0909090909090917 }, "geometry": { "type": "Point", "coordinates": [ -2.159252478859945, 54.959429380396585 ] } },
{ "type": "Feature", "properties": { "visible_points": 0, "total_points": 53, "visibility_pct": 0.0 }, "geometry": { "type": "Point", "coordinates": [ -2.15903609257077, 54.959429664752925 ] } },
{ "type": "Feature", "properties": { "visible_points": 5, "total_points": 55, "visibility_pct": 9.0909090909090917 }, "geometry": { "type": "Point", "coordinates": [ -2.159577487624988, 54.959536786488329 ] } },
{ "type": "Feature", "properties": { "visible_points": 3, "total_points": 55, "visibility_pct": 5.4545454545454541 }, "geometry": { "type": "Point", "coordinates": [ -2.159361100765092, 54.959537071421487 ] } },
{ "type": "Feature", "properties": { "visible_points": 0, "total_points": 55, "visibility_pct": 0.0 }, "geometry": { "type": "Point", "coordinates": [ -2.159144713901428, 54.959537355969559 ] } },
{ "type": "Feature", "properties": { "visible_points": 1, "total_points": 55, "visibility_pct": 1.8181818181818181 }, "geometry": { "type": "Point", "coordinates": [ -2.15968611068286, 54.95964447722406 ] } },
{ "type": "Feature", "properties": { "visible_points": 3, "total_points": 55, "visibility_pct": 5.4545454545454541 }, "geometry": { "type": "Point", "coordinates": [ -2.159469723248478, 54.959644762348979 ] } },
{ "type": "Feature", "properties": { "visible_points": 0, "total_points": 55, "visibility_pct": 0.0 }, "geometry": { "type": "Point", "coordinates": [ -2.159253335810325, 54.959645047088827 ] } },
{ "type": "Feature", "properties": { "visible_points": 3, "total_points": 48, "visibility_pct": 6.25 }, "geometry": { "type": "Point", "coordinates": [ -2.159794734318984, 54.959752167862412 ] } },
{ "type": "Feature", "properties": { "visible_points": 3, "total_points": 51, "visibility_pct": 5.8823529411764701 }, "geometry": { "type": "Point", "coordinates": [ -2.159578346310108, 54.959752453179085 ] } },
{ "type": "Feature", "properties": { "visible_points": 0, "total_points": 52, "visibility_pct": 0.0 }, "geometry": { "type": "Point", "coordinates": [ -2.159361958297461, 54.95975273811068 ] } },
{ "type": "Feature", "properties": { "visible_points": 2, "total_points": 44, "visibility_pct": 4.5454545454545459 }, "geometry": { "type": "Point", "coordinates": [ -2.159686969949989, 54.959860143911797 ] } },
{ "type": "Feature", "properties": { "visible_points": 1, "total_points": 46, "visibility_pct": 2.1739130434782608 }, "geometry": { "type": "Point", "coordinates": [ -2.159470581362846, 54.959860429035132 ] } }
]
}
