{
"type": "FeatureCollection",
"name": "REDCL_23_toilets",
"crs": { "type": "name", "properties": { "name": "urn:ogc:def:crs:OGC:1.3:CRS84" } },
"features": [
{ "type": "Feature", "properties": { "name": "Make do and Mend Library ", "payment_info": "Free", "accessible": "True", "radar": "False", "women": "True", "men": "True", "baby_change": "True", "Mon": "Closed", "Tue": "09:30-17:00", "Wed": "09:30-17:00", "Thu": "Closed", "Fri": "Closed", "Sat": "Closed", "Sun": "Closed", "index_right": 16, "park_offical_id": "REDCL_23" }, "geometry": { "type": "Point", "coordinates": [ -1.047735214, 54.605111255 ] } }
]
}
