{
"type": "FeatureCollection",
"name": "MIDDL_36",
"crs": { "type": "name", "properties": { "name": "urn:ogc:def:crs:OGC:1.3:CRS84" } },
"features": [
{ "type": "Feature", "properties": { "osm_id": 256892096, "name": null, "amenity": "bench", "man_made": null, "leisure": null, "playground": null, "memorial": null }, "geometry": { "type": "Point", "coordinates": [ -1.2392487, 54.5359853 ] } },
{ "type": "Feature", "properties": { "osm_id": 256891740, "name": null, "amenity": "bench", "man_made": null, "leisure": null, "playground": null, "memorial": null }, "geometry": { "type": "Point", "coordinates": [ -1.2367988, 54.5364435 ] } }
]
}
