{
"type": "FeatureCollection",
"name": "DURHA_358",
"crs": { "type": "name", "properties": { "name": "urn:ogc:def:crs:OGC:1.3:CRS84" } },
"features": [
{ "type": "Feature", "properties": { "osm_id": 4198662782, "name": null, "amenity": "bench", "man_made": null, "leisure": null, "playground": null, "memorial": null }, "geometry": { "type": "Point", "coordinates": [ -1.5769145, 54.772805 ] } },
{ "type": "Feature", "properties": { "osm_id": 4198662783, "name": null, "amenity": "bench", "man_made": null, "leisure": null, "playground": null, "memorial": null }, "geometry": { "type": "Point", "coordinates": [ -1.5769088, 54.772839 ] } },
{ "type": "Feature", "properties": { "osm_id": 4198662784, "name": null, "amenity": "bench", "man_made": null, "leisure": null, "playground": null, "memorial": null }, "geometry": { "type": "Point", "coordinates": [ -1.5769077, 54.7728757 ] } },
{ "type": "Feature", "properties": { "osm_id": 4198662781, "name": null, "amenity": "bench", "man_made": null, "leisure": null, "playground": null, "memorial": null }, "geometry": { "type": "Point", "coordinates": [ -1.576944, 54.772877 ] } }
]
}
