{
"type": "FeatureCollection",
"name": "DURHA_26",
"crs": { "type": "name", "properties": { "name": "urn:ogc:def:crs:OGC:1.3:CRS84" } },
"features": [
{ "type": "Feature", "properties": { "osm_id": 8617851975, "name": null, "amenity": "bench", "man_made": null, "leisure": null, "playground": null, "memorial": null }, "geometry": { "type": "Point", "coordinates": [ -1.5685841, 54.8773286 ] } },
{ "type": "Feature", "properties": { "osm_id": 8617861634, "name": null, "amenity": "bench", "man_made": null, "leisure": null, "playground": null, "memorial": null }, "geometry": { "type": "Point", "coordinates": [ -1.5674069, 54.87491 ] } },
{ "type": "Feature", "properties": { "osm_id": 8617851977, "name": null, "amenity": "bench", "man_made": null, "leisure": null, "playground": null, "memorial": null }, "geometry": { "type": "Point", "coordinates": [ -1.5678903, 54.8767214 ] } }
]
}
