{
"type": "FeatureCollection",
"name": "DURHA_11",
"crs": { "type": "name", "properties": { "name": "urn:ogc:def:crs:OGC:1.3:CRS84" } },
"features": [
{ "type": "Feature", "properties": { "osm_id": 10744204496, "name": null, "amenity": "bench", "man_made": null, "leisure": null, "playground": null, "memorial": null }, "geometry": { "type": "Point", "coordinates": [ -1.6574308, 54.6704606 ] } },
{ "type": "Feature", "properties": { "osm_id": 13630244702, "name": null, "amenity": "bench", "man_made": null, "leisure": null, "playground": null, "memorial": null }, "geometry": { "type": "Point", "coordinates": [ -1.6587646, 54.6735425 ] } },
{ "type": "Feature", "properties": { "osm_id": 9715747917, "name": null, "amenity": "bench", "man_made": null, "leisure": null, "playground": null, "memorial": null }, "geometry": { "type": "Point", "coordinates": [ -1.6654039, 54.6736839 ] } }
]
}
