{
"type": "FeatureCollection",
"name": "DURHA_20",
"crs": { "type": "name", "properties": { "name": "urn:ogc:def:crs:OGC:1.3:CRS84" } },
"features": [
{ "type": "Feature", "properties": { "osm_id": 11071850540, "name": null, "amenity": null, "man_made": null, "leisure": "picnic_table", "playground": null, "memorial": null }, "geometry": { "type": "Point", "coordinates": [ -1.572201, 54.770542 ] } }
]
}
