{
"type": "FeatureCollection",
"name": "HARTL_19",
"crs": { "type": "name", "properties": { "name": "urn:ogc:def:crs:OGC:1.3:CRS84" } },
"features": [
{ "type": "Feature", "properties": { "osm_id": 11833322918, "name": null, "amenity": "bench", "man_made": null, "leisure": null, "playground": null, "memorial": null }, "geometry": { "type": "Point", "coordinates": [ -1.2221769, 54.6612732 ] } },
{ "type": "Feature", "properties": { "osm_id": 11833336763, "name": null, "amenity": "bench", "man_made": null, "leisure": null, "playground": null, "memorial": null }, "geometry": { "type": "Point", "coordinates": [ -1.2221509, 54.6613261 ] } },
{ "type": "Feature", "properties": { "osm_id": 11833334057, "name": null, "amenity": "bench", "man_made": null, "leisure": null, "playground": null, "memorial": null }, "geometry": { "type": "Point", "coordinates": [ -1.2219415, 54.6615086 ] } },
{ "type": "Feature", "properties": { "osm_id": 11833334060, "name": null, "amenity": "bench", "man_made": null, "leisure": null, "playground": null, "memorial": null }, "geometry": { "type": "Point", "coordinates": [ -1.2216484, 54.6617956 ] } }
]
}
