{
"type": "FeatureCollection",
"name": "GATES_65_toilets",
"crs": { "type": "name", "properties": { "name": "urn:ogc:def:crs:OGC:1.3:CRS84" } },
"features": [
{ "type": "Feature", "properties": { "name": "Swalwell Visitor Centre", "payment_info": "Cost unknown", "accessible": "False", "radar": "Unknown", "women": "True", "men": "True", "baby_change": "False", "Mon": "Unknown", "Tue": "Unknown", "Wed": "Unknown", "Thu": "Unknown", "Fri": "Unknown", "Sat": "Unknown", "Sun": "Unknown", "index_right": 98, "park_offical_id": "GATES_65" }, "geometry": { "type": "Point", "coordinates": [ -1.690590149, 54.953478741 ] } },
{ "type": "Feature", "properties": { "name": "Asda Superstore ", "payment_info": "Free", "accessible": "True", "radar": "False", "women": "True", "men": "True", "baby_change": "True", "Mon": "07:00-00:00", "Tue": "00:00-00:00", "Wed": "00:00-00:00", "Thu": "00:00-00:00", "Fri": "00:00-00:00", "Sat": "00:00-22:00", "Sun": "11:00-17:00", "index_right": 98, "park_offical_id": "GATES_65" }, "geometry": { "type": "Point", "coordinates": [ -1.677698748, 54.959806051 ] } }
]
}
