{
"type": "FeatureCollection",
"name": "GATES_135_toilets",
"crs": { "type": "name", "properties": { "name": "urn:ogc:def:crs:OGC:1.3:CRS84" } },
"features": [
{ "type": "Feature", "properties": { "name": "Thornley Woodlands Visitor Centre", "payment_info": "Free", "accessible": "False", "radar": "Unknown", "women": "True", "men": "True", "baby_change": "False", "Mon": "09:00-18:00", "Tue": "09:00-18:00", "Wed": "09:00-18:00", "Thu": "09:00-18:00", "Fri": "09:00-18:00", "Sat": "09:00-18:00", "Sun": "09:00-18:00", "index_right": 31, "park_offical_id": "GATES_135" }, "geometry": { "type": "Point", "coordinates": [ -1.730006343, 54.933946605 ] } }
]
}
