{
"type": "FeatureCollection",
"name": "GATES_21_toilets",
"crs": { "type": "name", "properties": { "name": "urn:ogc:def:crs:OGC:1.3:CRS84" } },
"features": [
{ "type": "Feature", "properties": { "name": "Unknown", "payment_info": "Free", "accessible": "False", "radar": "Unknown", "women": "True", "men": "True", "baby_change": "True", "Mon": "Unknown", "Tue": "Unknown", "Wed": "Unknown", "Thu": "Unknown", "Fri": "Unknown", "Sat": "Unknown", "Sun": "Unknown", "index_right": 51, "park_offical_id": "GATES_21" }, "geometry": { "type": "Point", "coordinates": [ -1.7452425, 54.9832143 ] } },
{ "type": "Feature", "properties": { "name": "Ryton Park", "payment_info": "Cost unknown", "accessible": "False", "radar": "Unknown", "women": "True", "men": "True", "baby_change": "False", "Mon": "Unknown", "Tue": "Unknown", "Wed": "Unknown", "Thu": "Unknown", "Fri": "Unknown", "Sat": "Unknown", "Sun": "Unknown", "index_right": 51, "park_offical_id": "GATES_21" }, "geometry": { "type": "Point", "coordinates": [ -1.758721457, 54.975882885 ] } },
{ "type": "Feature", "properties": { "name": "Grainger Road Newburn Country Park", "payment_info": "Free", "accessible": "False", "radar": "Unknown", "women": "True", "men": "True", "baby_change": "True", "Mon": "Unknown", "Tue": "Unknown", "Wed": "Unknown", "Thu": "Unknown", "Fri": "Unknown", "Sat": "Unknown", "Sun": "Unknown", "index_right": 51, "park_offical_id": "GATES_21" }, "geometry": { "type": "Point", "coordinates": [ -1.745425418, 54.983449143 ] } }
]
}
