{
"type": "FeatureCollection",
"name": "GATES_63_toilets",
"crs": { "type": "name", "properties": { "name": "urn:ogc:def:crs:OGC:1.3:CRS84" } },
"features": [
{ "type": "Feature", "properties": { "name": "Ryton Park", "payment_info": "Cost unknown", "accessible": "False", "radar": "Unknown", "women": "True", "men": "True", "baby_change": "False", "Mon": "Unknown", "Tue": "Unknown", "Wed": "Unknown", "Thu": "Unknown", "Fri": "Unknown", "Sat": "Unknown", "Sun": "Unknown", "index_right": 96, "park_offical_id": "GATES_63" }, "geometry": { "type": "Point", "coordinates": [ -1.758721457, 54.975882885 ] } }
]
}
