{
"type": "FeatureCollection",
"name": "GATES_72_toilets",
"crs": { "type": "name", "properties": { "name": "urn:ogc:def:crs:OGC:1.3:CRS84" } },
"features": [
{ "type": "Feature", "properties": { "name": "Heworth Leisure Centre", "payment_info": "Free", "accessible": "False", "radar": "Unknown", "women": "True", "men": "True", "baby_change": "True", "Mon": "Unknown", "Tue": "Unknown", "Wed": "Unknown", "Thu": "Unknown", "Fri": "Unknown", "Sat": "Unknown", "Sun": "Unknown", "index_right": 106, "park_offical_id": "GATES_72" }, "geometry": { "type": "Point", "coordinates": [ -1.551914493, 54.946927208 ] } },
{ "type": "Feature", "properties": { "name": "Leam Lane Library", "payment_info": "Free", "accessible": "False", "radar": "Unknown", "women": "True", "men": "True", "baby_change": "True", "Mon": "Unknown", "Tue": "Unknown", "Wed": "Unknown", "Thu": "Unknown", "Fri": "Unknown", "Sat": "Unknown", "Sun": "Unknown", "index_right": 106, "park_offical_id": "GATES_72" }, "geometry": { "type": "Point", "coordinates": [ -1.546497011, 54.940005622 ] } }
]
}
