{
"type": "FeatureCollection",
"name": "NORTH_196",
"crs": { "type": "name", "properties": { "name": "urn:ogc:def:crs:OGC:1.3:CRS84" } },
"features": [
{ "type": "Feature", "properties": { "osm_id": 12187856123, "name": null, "amenity": "bench", "man_made": null, "leisure": null, "playground": null, "memorial": null }, "geometry": { "type": "Point", "coordinates": [ -1.9993893, 55.7670032 ] } },
{ "type": "Feature", "properties": { "osm_id": 7852683383, "name": null, "amenity": "bench", "man_made": null, "leisure": null, "playground": null, "memorial": null }, "geometry": { "type": "Point", "coordinates": [ -1.9991201, 55.767017 ] } },
{ "type": "Feature", "properties": { "osm_id": 7852687889, "name": null, "amenity": "bench", "man_made": null, "leisure": null, "playground": null, "memorial": null }, "geometry": { "type": "Point", "coordinates": [ -1.9990893, 55.7670658 ] } },
{ "type": "Feature", "properties": { "osm_id": 11163209987, "name": null, "amenity": "bench", "man_made": null, "leisure": null, "playground": null, "memorial": null }, "geometry": { "type": "Point", "coordinates": [ -1.9984382, 55.7671336 ] } }
]
}
