{
"type": "FeatureCollection",
"name": "NORTH_268",
"crs": { "type": "name", "properties": { "name": "urn:ogc:def:crs:OGC:1.3:CRS84" } },
"features": [
{ "type": "Feature", "properties": { "osm_id": 7840449741, "name": null, "amenity": "bench", "man_made": null, "leisure": null, "playground": null, "memorial": null }, "geometry": { "type": "Point", "coordinates": [ -1.6112276, 55.4508082 ] } },
{ "type": "Feature", "properties": { "osm_id": 7840449752, "name": null, "amenity": "bench", "man_made": null, "leisure": null, "playground": null, "memorial": null }, "geometry": { "type": "Point", "coordinates": [ -1.6112152, 55.450835 ] } },
{ "type": "Feature", "properties": { "osm_id": 7840449732, "name": null, "amenity": "bench", "man_made": null, "leisure": null, "playground": null, "memorial": null }, "geometry": { "type": "Point", "coordinates": [ -1.611195, 55.4508681 ] } }
]
}
