{
"type": "FeatureCollection",
"name": "NORTH_212",
"crs": { "type": "name", "properties": { "name": "urn:ogc:def:crs:OGC:1.3:CRS84" } },
"features": [
{ "type": "Feature", "properties": { "osm_id": 11163209971, "name": null, "amenity": null, "man_made": null, "leisure": "picnic_table", "playground": null, "memorial": null }, "geometry": { "type": "Point", "coordinates": [ -1.989279, 55.7555987 ] } },
{ "type": "Feature", "properties": { "osm_id": 11163209972, "name": null, "amenity": null, "man_made": null, "leisure": "picnic_table", "playground": null, "memorial": null }, "geometry": { "type": "Point", "coordinates": [ -1.989441, 55.7556846 ] } },
{ "type": "Feature", "properties": { "osm_id": 11163209973, "name": null, "amenity": null, "man_made": null, "leisure": "picnic_table", "playground": null, "memorial": null }, "geometry": { "type": "Point", "coordinates": [ -1.9896291, 55.7558483 ] } },
{ "type": "Feature", "properties": { "osm_id": 9566535011, "name": null, "amenity": "bench", "man_made": null, "leisure": null, "playground": null, "memorial": null }, "geometry": { "type": "Point", "coordinates": [ -1.9898391, 55.7560452 ] } }
]
}
