{
"type": "FeatureCollection",
"name": "NORTH_234",
"crs": { "type": "name", "properties": { "name": "urn:ogc:def:crs:OGC:1.3:CRS84" } },
"features": [
{ "type": "Feature", "properties": { "osm_id": 8922896611, "name": null, "amenity": "bench", "man_made": null, "leisure": null, "playground": null, "memorial": null }, "geometry": { "type": "Point", "coordinates": [ -2.010048, 55.5453758 ] } },
{ "type": "Feature", "properties": { "osm_id": 8922896614, "name": null, "amenity": "bench", "man_made": null, "leisure": null, "playground": null, "memorial": null }, "geometry": { "type": "Point", "coordinates": [ -2.0100979, 55.5455115 ] } },
{ "type": "Feature", "properties": { "osm_id": 8922896610, "name": null, "amenity": "bench", "man_made": null, "leisure": null, "playground": null, "memorial": null }, "geometry": { "type": "Point", "coordinates": [ -2.0102878, 55.5456699 ] } },
{ "type": "Feature", "properties": { "osm_id": 8922896612, "name": null, "amenity": "bench", "man_made": null, "leisure": null, "playground": null, "memorial": null }, "geometry": { "type": "Point", "coordinates": [ -2.0102262, 55.5458414 ] } }
]
}
