{
"type": "FeatureCollection",
"name": "NORTH_264",
"crs": { "type": "name", "properties": { "name": "urn:ogc:def:crs:OGC:1.3:CRS84" } },
"features": [
{ "type": "Feature", "properties": { "osm_id": 13630026859, "name": null, "amenity": "bench", "man_made": null, "leisure": null, "playground": null, "memorial": null }, "geometry": { "type": "Point", "coordinates": [ -1.6916354, 55.1679555 ] } },
{ "type": "Feature", "properties": { "osm_id": 13630026858, "name": null, "amenity": "bench", "man_made": null, "leisure": null, "playground": null, "memorial": null }, "geometry": { "type": "Point", "coordinates": [ -1.6915815, 55.1679634 ] } },
{ "type": "Feature", "properties": { "osm_id": 13630026860, "name": null, "amenity": "bench", "man_made": null, "leisure": null, "playground": null, "memorial": null }, "geometry": { "type": "Point", "coordinates": [ -1.6916768, 55.1679792 ] } },
{ "type": "Feature", "properties": { "osm_id": 13630026857, "name": null, "amenity": "bench", "man_made": null, "leisure": null, "playground": null, "memorial": null }, "geometry": { "type": "Point", "coordinates": [ -1.6915414, 55.1679918 ] } },
{ "type": "Feature", "properties": { "osm_id": 13630026861, "name": null, "amenity": "bench", "man_made": null, "leisure": null, "playground": null, "memorial": null }, "geometry": { "type": "Point", "coordinates": [ -1.6916423, 55.1680225 ] } },
{ "type": "Feature", "properties": { "osm_id": 13630026856, "name": null, "amenity": "bench", "man_made": null, "leisure": null, "playground": null, "memorial": null }, "geometry": { "type": "Point", "coordinates": [ -1.691547, 55.1680344 ] } },
{ "type": "Feature", "properties": { "osm_id": 13630026855, "name": null, "amenity": "bench", "man_made": null, "leisure": null, "playground": null, "memorial": null }, "geometry": { "type": "Point", "coordinates": [ -1.6914852, 55.168123 ] } },
{ "type": "Feature", "properties": { "osm_id": 13630026854, "name": null, "amenity": "bench", "man_made": null, "leisure": null, "playground": null, "memorial": null }, "geometry": { "type": "Point", "coordinates": [ -1.6914744, 55.1681806 ] } },
{ "type": "Feature", "properties": { "osm_id": 13630026853, "name": null, "amenity": "bench", "man_made": null, "leisure": null, "playground": null, "memorial": null }, "geometry": { "type": "Point", "coordinates": [ -1.6914641, 55.1682358 ] } }
]
}
