{
"type": "FeatureCollection",
"name": "NORTH_27",
"crs": { "type": "name", "properties": { "name": "urn:ogc:def:crs:OGC:1.3:CRS84" } },
"features": [
{ "type": "Feature", "properties": { "osm_id": 12115553537, "name": null, "amenity": "bench", "man_made": null, "leisure": null, "playground": null, "memorial": null }, "geometry": { "type": "Point", "coordinates": [ -2.0129129, 55.7743963 ] } },
{ "type": "Feature", "properties": { "osm_id": 12115506959, "name": null, "amenity": "bench", "man_made": null, "leisure": null, "playground": null, "memorial": null }, "geometry": { "type": "Point", "coordinates": [ -2.0115585, 55.7748527 ] } },
{ "type": "Feature", "properties": { "osm_id": 12115561744, "name": null, "amenity": "bench", "man_made": null, "leisure": null, "playground": null, "memorial": null }, "geometry": { "type": "Point", "coordinates": [ -2.0115818, 55.7748907 ] } },
{ "type": "Feature", "properties": { "osm_id": 12115524181, "name": null, "amenity": "bench", "man_made": null, "leisure": null, "playground": null, "memorial": null }, "geometry": { "type": "Point", "coordinates": [ -2.0110655, 55.7751848 ] } }
]
}
