{
"type": "FeatureCollection",
"name": "SOUTY_15_toilets",
"crs": { "type": "name", "properties": { "name": "urn:ogc:def:crs:OGC:1.3:CRS84" } },
"features": [
{ "type": "Feature", "properties": { "name": "The Word", "payment_info": "Cost unknown", "accessible": "True", "radar": "False", "women": "True", "men": "True", "baby_change": "Unknown", "Mon": "09:00-17:00", "Tue": "09:00-17:00", "Wed": "09:00-17:00", "Thu": "09:00-17:00", "Fri": "09:00-17:00", "Sat": "09:00-17:00", "Sun": "09:00-17:00", "index_right": 22, "park_offical_id": "SOUTY_15" }, "geometry": { "type": "Point", "coordinates": [ -1.43860817, 54.997176615 ] } },
{ "type": "Feature", "properties": { "name": "Market Place", "payment_info": "Free", "accessible": "True", "radar": "False", "women": "True", "men": "True", "baby_change": "False", "Mon": "Unknown", "Tue": "Unknown", "Wed": "Unknown", "Thu": "Unknown", "Fri": "Unknown", "Sat": "Unknown", "Sun": "Unknown", "index_right": 22, "park_offical_id": "SOUTY_15" }, "geometry": { "type": "Point", "coordinates": [ -1.438500881, 54.997923322 ] } },
{ "type": "Feature", "properties": { "name": "Queen Street South Shields", "payment_info": "Free", "accessible": "False", "radar": "Unknown", "women": "True", "men": "True", "baby_change": "True", "Mon": "09:00-17:00", "Tue": "09:00-17:00", "Wed": "09:00-17:00", "Thu": "09:00-17:00", "Fri": "09:00-17:00", "Sat": "09:00-17:00", "Sun": "09:00-17:00", "index_right": 22, "park_offical_id": "SOUTY_15" }, "geometry": { "type": "Point", "coordinates": [ -1.433657734, 54.998915039 ] } },
{ "type": "Feature", "properties": { "name": "Ocean Road South Shields", "payment_info": "Free", "accessible": "False", "radar": "Unknown", "women": "True", "men": "True", "baby_change": "True", "Mon": "09:00-18:30", "Tue": "09:00-18:30", "Wed": "09:00-18:30", "Thu": "09:00-18:30", "Fri": "09:00-18:30", "Sat": "09:00-18:30", "Sun": "09:00-18:30", "index_right": 22, "park_offical_id": "SOUTY_15" }, "geometry": { "type": "Point", "coordinates": [ -1.4279534, 54.9995912 ] } }
]
}
