{
"type": "FeatureCollection",
"name": "SOUTY_57_toilets",
"crs": { "type": "name", "properties": { "name": "urn:ogc:def:crs:OGC:1.3:CRS84" } },
"features": [
{ "type": "Feature", "properties": { "name": "Asda", "payment_info": "Free", "accessible": "True", "radar": "Unknown", "women": "True", "men": "True", "baby_change": "Unknown", "Mon": "Unknown", "Tue": "Unknown", "Wed": "Unknown", "Thu": "Unknown", "Fri": "Unknown", "Sat": "Unknown", "Sun": "Unknown", "index_right": 68, "park_offical_id": "SOUTY_57" }, "geometry": { "type": "Point", "coordinates": [ -1.463123497, 54.947684214 ] } }
]
}
