{
"type": "FeatureCollection",
"name": "HARTL_16_toilets",
"crs": { "type": "name", "properties": { "name": "urn:ogc:def:crs:OGC:1.3:CRS84" } },
"features": [
{ "type": "Feature", "properties": { "name": "Town Square", "payment_info": "Free", "accessible": "True", "radar": "False", "women": "True", "men": "True", "baby_change": "False", "Mon": "Unknown", "Tue": "Unknown", "Wed": "Unknown", "Thu": "Unknown", "Fri": "Unknown", "Sat": "Unknown", "Sun": "Unknown", "index_right": 6, "park_offical_id": "HARTL_16" }, "geometry": { "type": "Point", "coordinates": [ -1.1846468, 54.6958336 ] } },
{ "type": "Feature", "properties": { "name": "Unknown", "payment_info": "Free", "accessible": "False", "radar": "False", "women": "True", "men": "True", "baby_change": "False", "Mon": "Unknown", "Tue": "Unknown", "Wed": "Unknown", "Thu": "Unknown", "Fri": "Unknown", "Sat": "Unknown", "Sun": "Unknown", "index_right": 6, "park_offical_id": "HARTL_16" }, "geometry": { "type": "Point", "coordinates": [ -1.1760645, 54.6966363 ] } }
]
}
