{
"type": "FeatureCollection",
"name": "65c43033ded9_visibility",
"crs": { "type": "name", "properties": { "name": "urn:ogc:def:crs:OGC:1.3:CRS84" } },
"features": [
{ "type": "Feature", "properties": { "visible_points": 12, "total_points": 38, "visibility_pct": 31.578947368421051 }, "geometry": { "type": "Point", "coordinates": [ -1.593139332690026, 54.792399495793155 ] } },
{ "type": "Feature", "properties": { "visible_points": 5, "total_points": 44, "visibility_pct": 11.363636363636363 }, "geometry": { "type": "Point", "coordinates": [ -1.592923839462111, 54.79239877469125 ] } },
{ "type": "Feature", "properties": { "visible_points": 7, "total_points": 50, "visibility_pct": 14.000000000000002 }, "geometry": { "type": "Point", "coordinates": [ -1.592708346243787, 54.792398053206661 ] } },
{ "type": "Feature", "properties": { "visible_points": 7, "total_points": 53, "visibility_pct": 13.20754716981132 }, "geometry": { "type": "Point", "coordinates": [ -1.592492853035061, 54.792397331339416 ] } },
{ "type": "Feature", "properties": { "visible_points": 11, "total_points": 43, "visibility_pct": 25.581395348837212 }, "geometry": { "type": "Point", "coordinates": [ -1.593030507652, 54.792506968906658 ] } },
{ "type": "Feature", "properties": { "visible_points": 13, "total_points": 49, "visibility_pct": 26.530612244897959 }, "geometry": { "type": "Point", "coordinates": [ -1.592815013857038, 54.792506247610063 ] } },
{ "type": "Feature", "properties": { "visible_points": 9, "total_points": 53, "visibility_pct": 16.981132075471699 }, "geometry": { "type": "Point", "coordinates": [ -1.59259952007167, 54.792505525930807 ] } },
{ "type": "Feature", "properties": { "visible_points": 3, "total_points": 54, "visibility_pct": 5.5555555555555554 }, "geometry": { "type": "Point", "coordinates": [ -1.592384026295901, 54.792504803868887 ] } },
{ "type": "Feature", "properties": { "visible_points": 4, "total_points": 54, "visibility_pct": 7.4074074074074066 }, "geometry": { "type": "Point", "coordinates": [ -1.592168532529732, 54.792504081424276 ] } },
{ "type": "Feature", "properties": { "visible_points": 11, "total_points": 50, "visibility_pct": 22.0 }, "geometry": { "type": "Point", "coordinates": [ -1.591953038773177, 54.792503358597003 ] } },
{ "type": "Feature", "properties": { "visible_points": 5, "total_points": 44, "visibility_pct": 11.363636363636363 }, "geometry": { "type": "Point", "coordinates": [ -1.591737545026237, 54.792502635387066 ] } },
{ "type": "Feature", "properties": { "visible_points": 13, "total_points": 53, "visibility_pct": 24.528301886792452 }, "geometry": { "type": "Point", "coordinates": [ -1.592706187675297, 54.792613720427923 ] } },
{ "type": "Feature", "properties": { "visible_points": 12, "total_points": 54, "visibility_pct": 22.222222222222221 }, "geometry": { "type": "Point", "coordinates": [ -1.592490693322886, 54.792612998553999 ] } },
{ "type": "Feature", "properties": { "visible_points": 0, "total_points": 54, "visibility_pct": 0.0 }, "geometry": { "type": "Point", "coordinates": [ -1.592275198980068, 54.79261227629739 ] } },
{ "type": "Feature", "properties": { "visible_points": 7, "total_points": 51, "visibility_pct": 13.725490196078432 }, "geometry": { "type": "Point", "coordinates": [ -1.592059704646861, 54.792611553658112 ] } },
{ "type": "Feature", "properties": { "visible_points": 1, "total_points": 46, "visibility_pct": 2.1739130434782608 }, "geometry": { "type": "Point", "coordinates": [ -1.591844210323268, 54.792610830636171 ] } },
{ "type": "Feature", "properties": { "visible_points": 13, "total_points": 54, "visibility_pct": 24.074074074074073 }, "geometry": { "type": "Point", "coordinates": [ -1.592381865997424, 54.792720471076237 ] } },
{ "type": "Feature", "properties": { "visible_points": 13, "total_points": 51, "visibility_pct": 25.490196078431371 }, "geometry": { "type": "Point", "coordinates": [ -1.592166371087564, 54.792719748624961 ] } },
{ "type": "Feature", "properties": { "visible_points": 0, "total_points": 47, "visibility_pct": 0.0 }, "geometry": { "type": "Point", "coordinates": [ -1.591950876187313, 54.792719025791015 ] } },
{ "type": "Feature", "properties": { "visible_points": 0, "total_points": 41, "visibility_pct": 0.0 }, "geometry": { "type": "Point", "coordinates": [ -1.591735381296676, 54.792718302574386 ] } },
{ "type": "Feature", "properties": { "visible_points": 10, "total_points": 46, "visibility_pct": 21.739130434782609 }, "geometry": { "type": "Point", "coordinates": [ -1.59205754261838, 54.792827220851585 ] } },
{ "type": "Feature", "properties": { "visible_points": 4, "total_points": 42, "visibility_pct": 9.5238095238095237 }, "geometry": { "type": "Point", "coordinates": [ -1.59184204715108, 54.792826497822958 ] } }
]
}
