{
"type": "FeatureCollection",
"name": "e5654f114102_visibility",
"crs": { "type": "name", "properties": { "name": "urn:ogc:def:crs:OGC:1.3:CRS84" } },
"features": [
{ "type": "Feature", "properties": { "visible_points": 4, "total_points": 48, "visibility_pct": 8.3333333333333321 }, "geometry": { "type": "Point", "coordinates": [ -2.265685298880113, 54.904475609289534 ] } },
{ "type": "Feature", "properties": { "visible_points": 3, "total_points": 54, "visibility_pct": 5.5555555555555554 }, "geometry": { "type": "Point", "coordinates": [ -2.265469208967796, 54.904476082273725 ] } },
{ "type": "Feature", "properties": { "visible_points": 1, "total_points": 55, "visibility_pct": 1.8181818181818181 }, "geometry": { "type": "Point", "coordinates": [ -2.265253119049218, 54.904476554873732 ] } },
{ "type": "Feature", "properties": { "visible_points": 5, "total_points": 55, "visibility_pct": 9.0909090909090917 }, "geometry": { "type": "Point", "coordinates": [ -2.265037029124389, 54.904477027089499 ] } },
{ "type": "Feature", "properties": { "visible_points": 6, "total_points": 55, "visibility_pct": 10.909090909090908 }, "geometry": { "type": "Point", "coordinates": [ -2.264820939193315, 54.904477498921061 ] } },
{ "type": "Feature", "properties": { "visible_points": 6, "total_points": 50, "visibility_pct": 12.0 }, "geometry": { "type": "Point", "coordinates": [ -2.264604849255994, 54.904477970368426 ] } },
{ "type": "Feature", "properties": { "visible_points": 3, "total_points": 42, "visibility_pct": 7.1428571428571423 }, "geometry": { "type": "Point", "coordinates": [ -2.264388759312439, 54.90447844143155 ] } },
{ "type": "Feature", "properties": { "visible_points": 3, "total_points": 55, "visibility_pct": 5.4545454545454541 }, "geometry": { "type": "Point", "coordinates": [ -2.265361873970738, 54.904584151330738 ] } },
{ "type": "Feature", "properties": { "visible_points": 7, "total_points": 55, "visibility_pct": 12.727272727272727 }, "geometry": { "type": "Point", "coordinates": [ -2.265145783475097, 54.904584623747425 ] } },
{ "type": "Feature", "properties": { "visible_points": 7, "total_points": 55, "visibility_pct": 12.727272727272727 }, "geometry": { "type": "Point", "coordinates": [ -2.264929692973205, 54.904585095779915 ] } },
{ "type": "Feature", "properties": { "visible_points": 5, "total_points": 55, "visibility_pct": 9.0909090909090917 }, "geometry": { "type": "Point", "coordinates": [ -2.26471360246507, 54.904585567428164 ] } },
{ "type": "Feature", "properties": { "visible_points": 1, "total_points": 52, "visibility_pct": 1.9230769230769231 }, "geometry": { "type": "Point", "coordinates": [ -2.265470629469307, 54.904691747680879 ] } },
{ "type": "Feature", "properties": { "visible_points": 7, "total_points": 55, "visibility_pct": 12.727272727272727 }, "geometry": { "type": "Point", "coordinates": [ -2.265254538402852, 54.904692220298521 ] } },
{ "type": "Feature", "properties": { "visible_points": 9, "total_points": 55, "visibility_pct": 16.363636363636363 }, "geometry": { "type": "Point", "coordinates": [ -2.265038447330146, 54.904692692531931 ] } },
{ "type": "Feature", "properties": { "visible_points": 0, "total_points": 55, "visibility_pct": 0.0 }, "geometry": { "type": "Point", "coordinates": [ -2.264822356251191, 54.904693164381115 ] } },
{ "type": "Feature", "properties": { "visible_points": 12, "total_points": 48, "visibility_pct": 25.0 }, "geometry": { "type": "Point", "coordinates": [ -2.265579385544934, 54.904799343924182 ] } },
{ "type": "Feature", "properties": { "visible_points": 7, "total_points": 52, "visibility_pct": 13.461538461538462 }, "geometry": { "type": "Point", "coordinates": [ -2.265363293907666, 54.904799816742745 ] } },
{ "type": "Feature", "properties": { "visible_points": 9, "total_points": 55, "visibility_pct": 16.363636363636363 }, "geometry": { "type": "Point", "coordinates": [ -2.265147202264138, 54.904800289177089 ] } },
{ "type": "Feature", "properties": { "visible_points": 0, "total_points": 55, "visibility_pct": 0.0 }, "geometry": { "type": "Point", "coordinates": [ -2.264931110614364, 54.904800761227193 ] } },
{ "type": "Feature", "properties": { "visible_points": 10, "total_points": 47, "visibility_pct": 21.276595744680851 }, "geometry": { "type": "Point", "coordinates": [ -2.265472049989537, 54.90490741308011 ] } },
{ "type": "Feature", "properties": { "visible_points": 6, "total_points": 51, "visibility_pct": 11.76470588235294 }, "geometry": { "type": "Point", "coordinates": [ -2.26525595777519, 54.904907885715396 ] } }
]
}
