{
"type": "FeatureCollection",
"name": "GATES_19",
"crs": { "type": "name", "properties": { "name": "urn:ogc:def:crs:OGC:1.3:CRS84" } },
"features": [
{ "type": "Feature", "properties": { "osm_id": 4423693450, "name": null, "amenity": "bench", "man_made": null, "leisure": null, "playground": null, "memorial": null }, "geometry": { "type": "Point", "coordinates": [ -1.6741745, 54.9459481 ] } },
{ "type": "Feature", "properties": { "osm_id": 4423693449, "name": null, "amenity": "bench", "man_made": null, "leisure": null, "playground": null, "memorial": null }, "geometry": { "type": "Point", "coordinates": [ -1.6742516, 54.9459494 ] } },
{ "type": "Feature", "properties": { "osm_id": 4423693451, "name": null, "amenity": "bench", "man_made": null, "leisure": null, "playground": null, "memorial": null }, "geometry": { "type": "Point", "coordinates": [ -1.6741068, 54.9459508 ] } }
]
}
