{
"type": "FeatureCollection",
"name": "03d5f4d6912c_visibility",
"crs": { "type": "name", "properties": { "name": "urn:ogc:def:crs:OGC:1.3:CRS84" } },
"features": [
{ "type": "Feature", "properties": { "visible_points": 6, "total_points": 42, "visibility_pct": 14.285714285714285 }, "geometry": { "type": "Point", "coordinates": [ -1.689334050507962, 54.566484105487817 ] } },
{ "type": "Feature", "properties": { "visible_points": 5, "total_points": 43, "visibility_pct": 11.627906976744185 }, "geometry": { "type": "Point", "coordinates": [ -1.689119750707474, 54.566483556493502 ] } },
{ "type": "Feature", "properties": { "visible_points": 5, "total_points": 44, "visibility_pct": 11.363636363636363 }, "geometry": { "type": "Point", "coordinates": [ -1.688905450914264, 54.566483007119693 ] } },
{ "type": "Feature", "properties": { "visible_points": 4, "total_points": 48, "visibility_pct": 8.3333333333333321 }, "geometry": { "type": "Point", "coordinates": [ -1.689226079846208, 54.566591670128844 ] } },
{ "type": "Feature", "properties": { "visible_points": 0, "total_points": 49, "visibility_pct": 0.0 }, "geometry": { "type": "Point", "coordinates": [ -1.689011779481865, 54.566591120944821 ] } },
{ "type": "Feature", "properties": { "visible_points": 2, "total_points": 48, "visibility_pct": 4.1666666666666661 }, "geometry": { "type": "Point", "coordinates": [ -1.688797479124811, 54.566590571381248 ] } },
{ "type": "Feature", "properties": { "visible_points": 3, "total_points": 53, "visibility_pct": 5.6603773584905666 }, "geometry": { "type": "Point", "coordinates": [ -1.689118108613304, 54.566699234673131 ] } },
{ "type": "Feature", "properties": { "visible_points": 1, "total_points": 54, "visibility_pct": 1.8518518518518516 }, "geometry": { "type": "Point", "coordinates": [ -1.688903807685114, 54.566698685299379 ] } },
{ "type": "Feature", "properties": { "visible_points": 3, "total_points": 58, "visibility_pct": 5.1724137931034484 }, "geometry": { "type": "Point", "coordinates": [ -1.689010136812839, 54.566806799072346 ] } },
{ "type": "Feature", "properties": { "visible_points": 4, "total_points": 58, "visibility_pct": 6.8965517241379306 }, "geometry": { "type": "Point", "coordinates": [ -1.688795835321731, 54.566806249508119 ] } },
{ "type": "Feature", "properties": { "visible_points": 5, "total_points": 58, "visibility_pct": 8.6206896551724146 }, "geometry": { "type": "Point", "coordinates": [ -1.689116466512911, 54.566914912663648 ] } },
{ "type": "Feature", "properties": { "visible_points": 5, "total_points": 58, "visibility_pct": 8.6206896551724146 }, "geometry": { "type": "Point", "coordinates": [ -1.688902164454856, 54.56691436328633 ] } },
{ "type": "Feature", "properties": { "visible_points": 0, "total_points": 55, "visibility_pct": 0.0 }, "geometry": { "type": "Point", "coordinates": [ -1.689008494150474, 54.567022476925544 ] } },
{ "type": "Feature", "properties": { "visible_points": 3, "total_points": 54, "visibility_pct": 5.5555555555555554 }, "geometry": { "type": "Point", "coordinates": [ -1.688794191533662, 54.567021927354041 ] } },
{ "type": "Feature", "properties": { "visible_points": 2, "total_points": 49, "visibility_pct": 4.0816326530612246 }, "geometry": { "type": "Point", "coordinates": [ -1.689114824404837, 54.567130590472395 ] } },
{ "type": "Feature", "properties": { "visible_points": 0, "total_points": 49, "visibility_pct": 0.0 }, "geometry": { "type": "Point", "coordinates": [ -1.688900521222033, 54.567130041086187 ] } },
{ "type": "Feature", "properties": { "visible_points": 0, "total_points": 48, "visibility_pct": 0.0 }, "geometry": { "type": "Point", "coordinates": [ -1.688686218046462, 54.567129491320465 ] } },
{ "type": "Feature", "properties": { "visible_points": 4, "total_points": 44, "visibility_pct": 9.0909090909090917 }, "geometry": { "type": "Point", "coordinates": [ -1.689006851469153, 54.567238154725949 ] } },
{ "type": "Feature", "properties": { "visible_points": 2, "total_points": 43, "visibility_pct": 4.6511627906976747 }, "geometry": { "type": "Point", "coordinates": [ -1.688792547727588, 54.567237605145529 ] } },
{ "type": "Feature", "properties": { "visible_points": 2, "total_points": 38, "visibility_pct": 5.2631578947368416 }, "geometry": { "type": "Point", "coordinates": [ -1.688898877967461, 54.567345718878229 ] } }
]
}
