{
"type": "FeatureCollection",
"name": "SUNDE_101_toilets",
"crs": { "type": "name", "properties": { "name": "urn:ogc:def:crs:OGC:1.3:CRS84" } },
"features": [
{ "type": "Feature", "properties": { "name": "Marine walk", "payment_info": "Free", "accessible": "True", "radar": "True", "women": "True", "men": "True", "baby_change": "True", "Mon": "09:00-17:00", "Tue": "09:00-17:00", "Wed": "09:00-17:00", "Thu": "09:00-17:00", "Fri": "09:00-17:00", "Sat": "09:00-17:00", "Sun": "09:00-17:00", "index_right": 4, "park_offical_id": "SUNDE_101" }, "geometry": { "type": "Point", "coordinates": [ -1.364293406, 54.920597356 ] } },
{ "type": "Feature", "properties": { "name": "Park Parade", "payment_info": "Free", "accessible": "False", "radar": "Unknown", "women": "True", "men": "True", "baby_change": "Unknown", "Mon": "06:00-18:00", "Tue": "06:00-18:00", "Wed": "06:00-18:00", "Thu": "06:00-18:00", "Fri": "06:00-18:00", "Sat": "06:00-18:00", "Sun": "06:00-18:00", "index_right": 4, "park_offical_id": "SUNDE_101" }, "geometry": { "type": "Point", "coordinates": [ -1.371338343, 54.922502228 ] } }
]
}
