{
"type": "FeatureCollection",
"name": "NEWUP_60_toilets",
"crs": { "type": "name", "properties": { "name": "urn:ogc:def:crs:OGC:1.3:CRS84" } },
"features": [
{ "type": "Feature", "properties": { "name": "West Road Crematorium West Road", "payment_info": "Free", "accessible": "False", "radar": "Unknown", "women": "True", "men": "True", "baby_change": "True", "Mon": "Unknown", "Tue": "Unknown", "Wed": "Unknown", "Thu": "Unknown", "Fri": "Unknown", "Sat": "Unknown", "Sun": "Unknown", "index_right": 120, "park_offical_id": "NEWUP_60" }, "geometry": { "type": "Point", "coordinates": [ -1.703139808, 54.992204747 ] } }
]
}
