{
"type": "FeatureCollection",
"name": "NEWUP_156_toilets",
"crs": { "type": "name", "properties": { "name": "urn:ogc:def:crs:OGC:1.3:CRS84" } },
"features": [
{ "type": "Feature", "properties": { "name": "Jesmond Dene Visitor Centre", "payment_info": "Free", "accessible": "True", "radar": "Unknown", "women": "True", "men": "True", "baby_change": "Unknown", "Mon": "09:00-17:00", "Tue": "09:00-17:00", "Wed": "09:00-17:00", "Thu": "09:00-17:00", "Fri": "09:00-17:00", "Sat": "09:00-16:30", "Sun": "09:00-16:30", "index_right": 47, "park_offical_id": "NEWUP_156" }, "geometry": { "type": "Point", "coordinates": [ -1.592129081, 54.990453721 ] } }
]
}
