{
"type": "FeatureCollection",
"name": "SUNDE_52",
"crs": { "type": "name", "properties": { "name": "urn:ogc:def:crs:OGC:1.3:CRS84" } },
"features": [
{ "type": "Feature", "properties": { "osm_id": 9381860651, "name": null, "amenity": "bench", "man_made": null, "leisure": null, "playground": null, "memorial": null }, "geometry": { "type": "Point", "coordinates": [ -1.476375, 54.8749608 ] } },
{ "type": "Feature", "properties": { "osm_id": 9381860650, "name": null, "amenity": "bench", "man_made": null, "leisure": null, "playground": null, "memorial": null }, "geometry": { "type": "Point", "coordinates": [ -1.4692873, 54.8751584 ] } },
{ "type": "Feature", "properties": { "osm_id": 9381860649, "name": null, "amenity": "bench", "man_made": null, "leisure": null, "playground": null, "memorial": null }, "geometry": { "type": "Point", "coordinates": [ -1.4676887, 54.8770225 ] } },
{ "type": "Feature", "properties": { "osm_id": 8828317893, "name": null, "amenity": null, "man_made": null, "leisure": "picnic_table", "playground": null, "memorial": null }, "geometry": { "type": "Point", "coordinates": [ -1.4711804, 54.8776608 ] } },
{ "type": "Feature", "properties": { "osm_id": 8828317877, "name": null, "amenity": null, "man_made": null, "leisure": "picnic_table", "playground": null, "memorial": null }, "geometry": { "type": "Point", "coordinates": [ -1.470837, 54.8776665 ] } },
{ "type": "Feature", "properties": { "osm_id": 8828317867, "name": null, "amenity": null, "man_made": null, "leisure": "picnic_table", "playground": null, "memorial": null }, "geometry": { "type": "Point", "coordinates": [ -1.4710431, 54.8777091 ] } },
{ "type": "Feature", "properties": { "osm_id": 8828317885, "name": null, "amenity": "bench", "man_made": null, "leisure": null, "playground": null, "memorial": null }, "geometry": { "type": "Point", "coordinates": [ -1.4790802, 54.8781772 ] } }
]
}
