{
"type": "FeatureCollection",
"name": "SUNDE_62",
"crs": { "type": "name", "properties": { "name": "urn:ogc:def:crs:OGC:1.3:CRS84" } },
"features": [
{ "type": "Feature", "properties": { "osm_id": 2594015182, "name": null, "amenity": "bench", "man_made": null, "leisure": null, "playground": null, "memorial": null }, "geometry": { "type": "Point", "coordinates": [ -1.3787346, 54.9026468 ] } },
{ "type": "Feature", "properties": { "osm_id": 2594015183, "name": null, "amenity": "bench", "man_made": null, "leisure": null, "playground": null, "memorial": null }, "geometry": { "type": "Point", "coordinates": [ -1.3788723, 54.9031382 ] } },
{ "type": "Feature", "properties": { "osm_id": 2594015221, "name": null, "amenity": "bench", "man_made": null, "leisure": null, "playground": null, "memorial": null }, "geometry": { "type": "Point", "coordinates": [ -1.3792076, 54.903573 ] } },
{ "type": "Feature", "properties": { "osm_id": 2594015241, "name": null, "amenity": "bench", "man_made": null, "leisure": null, "playground": null, "memorial": null }, "geometry": { "type": "Point", "coordinates": [ -1.379044, 54.9038021 ] } }
]
}
