{
"type": "FeatureCollection",
"name": "DARLI_42",
"crs": { "type": "name", "properties": { "name": "urn:ogc:def:crs:OGC:1.3:CRS84" } },
"features": [
{ "type": "Feature", "properties": { "osm_id": 8807033963, "name": null, "amenity": "bench", "man_made": null, "leisure": null, "playground": null, "memorial": null }, "geometry": { "type": "Point", "coordinates": [ -1.5515974, 54.52319 ] } },
{ "type": "Feature", "properties": { "osm_id": 8807033964, "name": null, "amenity": "bench", "man_made": null, "leisure": null, "playground": null, "memorial": null }, "geometry": { "type": "Point", "coordinates": [ -1.5514748, 54.5234734 ] } }
]
}
