{
"type": "FeatureCollection",
"name": "DURHA_415_toilets",
"crs": { "type": "name", "properties": { "name": "urn:ogc:def:crs:OGC:1.3:CRS84" } },
"features": [
{ "type": "Feature", "properties": { "name": "County Hall", "payment_info": "Free", "accessible": "False", "radar": "Unknown", "women": "True", "men": "True", "baby_change": "Unknown", "Mon": "09:00-17:00", "Tue": "09:00-17:00", "Wed": "09:00-17:00", "Thu": "09:00-17:00", "Fri": "09:00-17:00", "Sat": "Closed", "Sun": "Closed", "index_right": 261, "park_offical_id": "DURHA_415" }, "geometry": { "type": "Point", "coordinates": [ -1.585174799, 54.78550564 ] } }
]
}
