{
"type": "FeatureCollection",
"name": "DURHA_80_toilets",
"crs": { "type": "name", "properties": { "name": "urn:ogc:def:crs:OGC:1.3:CRS84" } },
"features": [
{ "type": "Feature", "properties": { "name": "Locomotion museum", "payment_info": "Free", "accessible": "True", "radar": "Unknown", "women": "True", "men": "True", "baby_change": "Unknown", "Mon": "Unknown", "Tue": "Unknown", "Wed": "Unknown", "Thu": "Unknown", "Fri": "Unknown", "Sat": "Unknown", "Sun": "Unknown", "index_right": 399, "park_offical_id": "DURHA_80" }, "geometry": { "type": "Point", "coordinates": [ -1.629924774, 54.624003018 ] } },
{ "type": "Feature", "properties": { "name": "No name", "payment_info": "Cost unknown", "accessible": "True", "radar": "Unknown", "women": "Unknown", "men": "Unknown", "baby_change": "Unknown", "Mon": "09:00-18:00", "Tue": "09:00-18:00", "Wed": "09:00-18:00", "Thu": "09:00-18:00", "Fri": "09:00-18:00", "Sat": "09:00-18:00", "Sun": "09:00-18:00", "index_right": 399, "park_offical_id": "DURHA_80" }, "geometry": { "type": "Point", "coordinates": [ -1.643850803, 54.634449165 ] } }
]
}
