{
"type": "FeatureCollection",
"name": "DURHA_354_toilets",
"crs": { "type": "name", "properties": { "name": "urn:ogc:def:crs:OGC:1.3:CRS84" } },
"features": [
{ "type": "Feature", "properties": { "name": "Morrisons Chester le street", "payment_info": "Cost unknown", "accessible": "True", "radar": "Unknown", "women": "True", "men": "True", "baby_change": "True", "Mon": "09:00-17:00", "Tue": "09:00-17:00", "Wed": "09:00-17:00", "Thu": "09:00-17:00", "Fri": "09:00-17:00", "Sat": "09:00-17:00", "Sun": "09:00-17:00", "index_right": 223, "park_offical_id": "DURHA_354" }, "geometry": { "type": "Point", "coordinates": [ -1.575797796, 54.857133204 ] } }
]
}
