{
"type": "FeatureCollection",
"name": "DURHA_473_toilets",
"crs": { "type": "name", "properties": { "name": "urn:ogc:def:crs:OGC:1.3:CRS84" } },
"features": [
{ "type": "Feature", "properties": { "name": "Unknown", "payment_info": "Free", "accessible": "False", "radar": "Unknown", "women": "Unknown", "men": "Unknown", "baby_change": "Unknown", "Mon": "Unknown", "Tue": "Unknown", "Wed": "Unknown", "Thu": "Unknown", "Fri": "Unknown", "Sat": "Unknown", "Sun": "Unknown", "index_right": 291, "park_offical_id": "DURHA_473" }, "geometry": { "type": "Point", "coordinates": [ -1.4525418, 54.8212885 ] } },
{ "type": "Feature", "properties": { "name": "Hetton Centre", "payment_info": "Free", "accessible": "False", "radar": "Unknown", "women": "True", "men": "True", "baby_change": "Unknown", "Mon": "06:00-18:00", "Tue": "06:00-18:00", "Wed": "06:00-18:00", "Thu": "06:00-18:00", "Fri": "06:00-18:00", "Sat": "06:00-18:00", "Sun": "06:00-18:00", "index_right": 291, "park_offical_id": "DURHA_473" }, "geometry": { "type": "Point", "coordinates": [ -1.454412469, 54.821571838 ] } }
]
}
