{
"type": "FeatureCollection",
"name": "DURHA_369_toilets",
"crs": { "type": "name", "properties": { "name": "urn:ogc:def:crs:OGC:1.3:CRS84" } },
"features": [
{ "type": "Feature", "properties": { "name": "Sunderland Minster ", "payment_info": "Free", "accessible": "True", "radar": "False", "women": "True", "men": "True", "baby_change": "True", "Mon": "10:00-14:30", "Tue": "10:00-14:30", "Wed": "10:00-14:30", "Thu": "10:00-14:30", "Fri": "10:00-14:30", "Sat": "10:00-14:30", "Sun": "10:00-14:30", "index_right": 232, "park_offical_id": "DURHA_369" }, "geometry": { "type": "Point", "coordinates": [ -1.388865232, 54.905771312 ] } },
{ "type": "Feature", "properties": { "name": "Park Lane", "payment_info": "Free", "accessible": "False", "radar": "Unknown", "women": "True", "men": "True", "baby_change": "Unknown", "Mon": "06:00-20:00", "Tue": "06:00-20:00", "Wed": "06:00-20:00", "Thu": "06:00-20:00", "Fri": "06:00-20:00", "Sat": "06:00-20:00", "Sun": "06:00-20:00", "index_right": 232, "park_offical_id": "DURHA_369" }, "geometry": { "type": "Point", "coordinates": [ -1.384754777, 54.90543683 ] } },
{ "type": "Feature", "properties": { "name": "Transport Interchange", "payment_info": "000", "accessible": "True", "radar": "True", "women": "True", "men": "True", "baby_change": "False", "Mon": "06:00-23:00", "Tue": "06:00-23:00", "Wed": "06:00-23:00", "Thu": "06:00-23:00", "Fri": "06:00-23:00", "Sat": "06:00-23:00", "Sun": "06:00-23:00", "index_right": 232, "park_offical_id": "DURHA_369" }, "geometry": { "type": "Point", "coordinates": [ -1.38535111, 54.902929479 ] } },
{ "type": "Feature", "properties": { "name": "Sunderland Station ", "payment_info": "Free", "accessible": "True", "radar": "True", "women": "True", "men": "True", "baby_change": "Unknown", "Mon": "Unknown", "Tue": "Unknown", "Wed": "Unknown", "Thu": "Unknown", "Fri": "Unknown", "Sat": "Unknown", "Sun": "Unknown", "index_right": 232, "park_offical_id": "DURHA_369" }, "geometry": { "type": "Point", "coordinates": [ -1.38258948, 54.905386783 ] } }
]
}
