{
"type": "FeatureCollection",
"name": "DURHA_103_toilets",
"crs": { "type": "name", "properties": { "name": "urn:ogc:def:crs:OGC:1.3:CRS84" } },
"features": [
{ "type": "Feature", "properties": { "name": "Woodhouse Park", "payment_info": "Free", "accessible": "True", "radar": "Unknown", "women": "True", "men": "True", "baby_change": "Unknown", "Mon": "Unknown", "Tue": "Unknown", "Wed": "Unknown", "Thu": "Unknown", "Fri": "Unknown", "Sat": "Unknown", "Sun": "Unknown", "index_right": 12, "park_offical_id": "DURHA_103" }, "geometry": { "type": "Point", "coordinates": [ -1.351799858, 54.759602758 ] } }
]
}
