{
"type": "FeatureCollection",
"name": "DURHA_180_toilets",
"crs": { "type": "name", "properties": { "name": "urn:ogc:def:crs:OGC:1.3:CRS84" } },
"features": [
{ "type": "Feature", "properties": { "name": "Morrisons", "payment_info": "Free", "accessible": "True", "radar": "True", "women": "True", "men": "True", "baby_change": "Unknown", "Mon": "07:00-21:00", "Tue": "07:00-21:00", "Wed": "07:00-21:00", "Thu": "07:00-21:00", "Fri": "07:00-21:00", "Sat": "07:00-21:00", "Sun": "10:00-16:00", "index_right": 96, "park_offical_id": "DURHA_180" }, "geometry": { "type": "Point", "coordinates": [ -1.678172536, 54.658703522 ] } },
{ "type": "Feature", "properties": { "name": "Asda", "payment_info": "Free", "accessible": "True", "radar": "True", "women": "True", "men": "True", "baby_change": "Unknown", "Mon": "07:00-22:00", "Tue": "07:00-22:00", "Wed": "07:00-22:00", "Thu": "07:00-22:00", "Fri": "07:00-22:00", "Sat": "07:00-22:00", "Sun": "10:00-16:00", "index_right": 96, "park_offical_id": "DURHA_180" }, "geometry": { "type": "Point", "coordinates": [ -1.674116675, 54.657784986 ] } }
]
}
