{
"type": "FeatureCollection",
"name": "NORTY_62_toilets",
"crs": { "type": "name", "properties": { "name": "urn:ogc:def:crs:OGC:1.3:CRS84" } },
"features": [
{ "type": "Feature", "properties": { "name": "Oxford Centre West Farm Avenue", "payment_info": "Free", "accessible": "False", "radar": "True", "women": "True", "men": "True", "baby_change": "True", "Mon": "Unknown", "Tue": "Unknown", "Wed": "Unknown", "Thu": "Unknown", "Fri": "Unknown", "Sat": "Unknown", "Sun": "Unknown", "index_right": 65, "park_offical_id": "NORTY_62" }, "geometry": { "type": "Point", "coordinates": [ -1.58924371, 55.011573415 ] } }
]
}
