{
"type": "FeatureCollection",
"name": "NORTY_22_toilets",
"crs": { "type": "name", "properties": { "name": "urn:ogc:def:crs:OGC:1.3:CRS84" } },
"features": [
{ "type": "Feature", "properties": { "name": "Unknown", "payment_info": "Free", "accessible": "False", "radar": "True", "women": "True", "men": "True", "baby_change": "True", "Mon": "07:30-21:00", "Tue": "07:30-21:00", "Wed": "07:30-21:00", "Thu": "07:30-21:00", "Fri": "07:30-21:00", "Sat": "07:30-21:00", "Sun": "07:30-21:00", "index_right": 21, "park_offical_id": "NORTY_22" }, "geometry": { "type": "Point", "coordinates": [ -1.528920829, 55.019628692 ] } }
]
}
