{
"type": "FeatureCollection",
"name": "STOCK_86_toilets",
"crs": { "type": "name", "properties": { "name": "urn:ogc:def:crs:OGC:1.3:CRS84" } },
"features": [
{ "type": "Feature", "properties": { "name": "Wynyard Woodland Park", "payment_info": "Cost unknown", "accessible": "False", "radar": "Unknown", "women": "True", "men": "True", "baby_change": "False", "Mon": "09:00-21:00", "Tue": "09:00-21:00", "Wed": "09:00-21:00", "Thu": "09:00-21:00", "Fri": "09:00-21:00", "Sat": "09:00-21:00", "Sun": "09:00-21:00", "index_right": 101, "park_offical_id": "STOCK_86" }, "geometry": { "type": "Point", "coordinates": [ -1.378244917, 54.612488352 ] } }
]
}
