{
"type": "FeatureCollection",
"name": "STOCK_1_toilets",
"crs": { "type": "name", "properties": { "name": "urn:ogc:def:crs:OGC:1.3:CRS84" } },
"features": [
{ "type": "Feature", "properties": { "name": "Cafe in the Park John Whitehead Park", "payment_info": "Free", "accessible": "True", "radar": "Unknown", "women": "True", "men": "True", "baby_change": "True", "Mon": "Unknown", "Tue": "Unknown", "Wed": "Unknown", "Thu": "Unknown", "Fri": "Unknown", "Sat": "Unknown", "Sun": "Unknown", "index_right": 1, "park_offical_id": "STOCK_1" }, "geometry": { "type": "Point", "coordinates": [ -1.289895773, 54.608690716 ] } }
]
}
