{
"type": "FeatureCollection",
"name": "DARLI_22_toilets",
"crs": { "type": "name", "properties": { "name": "urn:ogc:def:crs:OGC:1.3:CRS84" } },
"features": [
{ "type": "Feature", "properties": { "name": "Dolphin Centre", "payment_info": "Free", "accessible": "True", "radar": "True", "women": "False", "men": "False", "baby_change": "True", "Mon": "06:30-21:00", "Tue": "06:30-21:00", "Wed": "06:30-21:00", "Thu": "06:30-21:00", "Fri": "06:30-21:00", "Sat": "08:00-21:00", "Sun": "08:00-19:00", "index_right": 15, "park_offical_id": "DARLI_22" }, "geometry": { "type": "Point", "coordinates": [ -1.553556919, 54.523995652 ] } },
{ "type": "Feature", "properties": { "name": "Willinsons Toilet", "payment_info": "Free", "accessible": "False", "radar": "True", "women": "True", "men": "True", "baby_change": "False", "Mon": "08:00-20:00", "Tue": "08:00-20:00", "Wed": "08:00-20:00", "Thu": "08:00-20:00", "Fri": "08:00-20:00", "Sat": "08:00-20:00", "Sun": "08:00-20:00", "index_right": 15, "park_offical_id": "DARLI_22" }, "geometry": { "type": "Point", "coordinates": [ -1.55241418, 54.526800493 ] } }
]
}
